LICENSE
README.md
python_template/__init__.py
python_template/__main__.py
python_template/cli.py
python_template_x-0.4.1.dist-info/LICENSE
python_template_x-0.4.1.dist-info/METADATA
python_template_x-0.4.1.dist-info/WHEEL
python_template_x-0.4.1.dist-info/entry_points.txt
python_template_x-0.4.1.dist-info/RECORD
