Metadata-Version: 2.1
Name: python-template-x
Version: 0.4.1
Summary: This is a python template.
License: MIT
Keywords: app,cli,python,template
Author: Mark Beacom
Author-email: m@beacom.dev
Requires-Python: >=3.9,<4.0
Classifier: License :: OSI Approved :: MIT License
Classifier: Programming Language :: Python
Classifier: Programming Language :: Python :: 3
Classifier: Programming Language :: Python :: 3.9
Classifier: Programming Language :: Python :: 3.10
Classifier: Programming Language :: Python :: 3.11
Classifier: Programming Language :: Python :: 3.12
Classifier: Programming Language :: Python :: 3.13
Requires-Dist: pip (>=24.0)
Requires-Dist: typer[all] (>=0.12.5,<0.13.0)
